<?xml version="1.0" encoding="utf-8" ?>
<bulletDefinitions>
  <JDBullet>
    <Id>1</Id>
    <Name>Bullet 1</Name>
    <Unlocked>true</Unlocked>
    <AccessedLevel>0</AccessedLevel>
    <ZombieKillNumber>1</ZombieKillNumber>
    <bulletDebugChar>@</bulletDebugChar>
    <ResourceName>Bullets/CyanBullet</ResourceName>
  </JDBullet>
  <JDBullet>
    <Id>2</Id>
    <Name>Bullet 2</Name>
    <Unlocked>true</Unlocked>
    <AccessedLevel>0</AccessedLevel>
    <ZombieKillNumber>2</ZombieKillNumber>
    <bulletDebugChar>#</bulletDebugChar>
    <ResourceName>Bullets/BlueBullet</ResourceName>
  </JDBullet>
  <JDBullet>
    <Id>3</Id>
    <Name>Bullet 3</Name>
    <Unlocked>true</Unlocked>
    <AccessedLevel>0</AccessedLevel>
    <ZombieKillNumber>3</ZombieKillNumber>
    <bulletDebugChar>%</bulletDebugChar>
    <ResourceName>Bullets/RedBullet</ResourceName>
  </JDBullet>
  <JDBullet>
    <Id>4</Id>
    <Name>Bullet 4</Name>
    <Unlocked>true</Unlocked>
    <AccessedLevel>0</AccessedLevel>
    <ZombieKillNumber>4</ZombieKillNumber>
    <bulletDebugChar>*</bulletDebugChar>
    <ResourceName>Bullets/YellowBullet</ResourceName>
  </JDBullet>
  <JDBullet>
    <Id>5</Id>
    <Name>Bullet 5</Name>
    <Unlocked>true</Unlocked>
    <AccessedLevel>0</AccessedLevel>
    <ZombieKillNumber>5</ZombieKillNumber>
    <bulletDebugChar>X</bulletDebugChar>
    <ResourceName>Bullets/GreenBullet</ResourceName>
  </JDBullet>

</bulletDefinitions>